ankur/__init__.py
ankur/cli.py
ankur/hello.py
ankur-0.3.0.dist-info/METADATA
ankur-0.3.0.dist-info/WHEEL
ankur-0.3.0.dist-info/entry_points.txt
ankur-0.3.0.dist-info/top_level.txt
ankur-0.3.0.dist-info/RECORD
