Metadata-Version: 2.4
Name: ankur
Version: 0.3.0
Summary: Ankur's package with CLI support
Home-page: https://github.com/7007259Ankur
Author: Ankur
Author-email: ankurkumar7753@gmail.com
Requires-Dist: colorama>=0.4.6
Dynamic: author
Dynamic: author-email
Dynamic: home-page
Dynamic: requires-dist
Dynamic: summary
